deepeval_plugin/__init__.py
deepeval_plugin/__version__.py
deepeval_plugin/admin.py
deepeval_plugin/apps.py
deepeval_plugin/decorators.py
deepeval_plugin/models.py
deepeval_plugin/plugin.py
deepeval_plugin/signals.py
deepeval_plugin/tasks.py
deepeval_plugin/types.py
deepeval_plugin/urls.py
deepeval_plugin/utils.py
deepeval_plugin/views.py
deepeval_plugin/migrations/0001_initial.py
deepeval_plugin/migrations/0002_answerrelevance.py
deepeval_plugin/migrations/0003_remove_answerrelevance_relevance_and_more.py
deepeval_plugin/migrations/0004_data_source_id.py
deepeval_plugin/migrations/0005_contextualrelevancy_faithfulness_hallucination_and_more.py
deepeval_plugin/migrations/0006_settings.py
deepeval_plugin/migrations/__init__.py
deepeval_plugin/templates/deepeval_plugin/components/answer_relevance.html
deepeval_plugin/templates/deepeval_plugin/components/contextual_relevancy.html
deepeval_plugin/templates/deepeval_plugin/components/faithfulness.html
deepeval_plugin/templates/deepeval_plugin/components/hallucination.html
deepeval_plugin/templates/deepeval_plugin/components/modal.html
deepeval_plugin/templates/deepeval_plugin/components/toast.html
deepeval_plugin/templates/deepeval_plugin/components/toxicity.html
deepeval_plugin/templates/deepeval_plugin/htmx/check_results.html
deepeval_plugin/templates/deepeval_plugin/htmx/evaluation_test.html
deepeval_plugin/templates/deepeval_plugin/pages/dataset.html
deepeval_plugin/templates/deepeval_plugin/pages/home.html
deepeval_plugin/templates/deepeval_plugin/pages/settings.html
deepeval_plugin/templates/deepeval_plugin/widgets/chat_widget.html
deepeval_plugin/templates/deepeval_plugin/widgets/disabled_widget.html
deepeval_plugin/tests/__init__.py
deepeval_plugin/tests/settings.py
deepeval_plugin/tests/test_django.py
deepeval_plugin/tests/test_routes.py
deepeval_plugin-0.2.3.dist-info/METADATA
deepeval_plugin-0.2.3.dist-info/WHEEL
deepeval_plugin-0.2.3.dist-info/entry_points.txt
deepeval_plugin-0.2.3.dist-info/licenses/LICENSE
deepeval_plugin-0.2.3.dist-info/RECORD
