Metadata-Version: 2.4
Name: deepeval_plugin
Version: 0.2.3
Author-email: epuerta <esteban_puerta@rhinosearch.io>
License-File: LICENSE
Classifier: Programming Language :: Python :: 3 :: Only
Classifier: Programming Language :: Python :: 3.11
Classifier: Programming Language :: Python :: 3.12
Requires-Python: >=3.11
Requires-Dist: boto3
Requires-Dist: deepeval
Requires-Dist: django
Requires-Dist: djp
